std_encode/__init__.py
std_encode/console.py
std_encode-0.2.3.dist-info/entry_points.txt
std_encode-0.2.3.dist-info/LICENSE.txt
std_encode-0.2.3.dist-info/WHEEL
std_encode-0.2.3.dist-info/METADATA
std_encode-0.2.3.dist-info/RECORD
