Metadata-Version: 2.1
Name: std-encode
Version: 0.2.3
Summary: Encode and decode files through the standard input/output
Home-page: https://github.com/jaimebuelta/std_encode
License: MIT
Author: Jaime Buelta
Author-email: jaime.buelta@gmail.com
Requires-Python: >=3.5,<4
Classifier: License :: OSI Approved :: MIT License
Classifier: Programming Language :: Python :: 3
Classifier: Programming Language :: Python :: 3.5
Classifier: Programming Language :: Python :: 3.6
Classifier: Programming Language :: Python :: 3.7
Project-URL: Repository, https://github.com/jaimebuelta/std_encode
